dataplicity/__init__.py
dataplicity/__main__.py
dataplicity/_version.py
dataplicity/app.py
dataplicity/client.py
dataplicity/clockcheck.py
dataplicity/compat.py
dataplicity/constants.py
dataplicity/device_meta.py
dataplicity/disk_tools.py
dataplicity/iptool.py
dataplicity/jsonrpc.py
dataplicity/m2mmanager.py
dataplicity/portforward.py
dataplicity/rpi.py
dataplicity/subcommand.py
dataplicity/m2m/__init__.py
dataplicity/m2m/bencode.py
dataplicity/m2m/commandservice.py
dataplicity/m2m/dispatcher.py
dataplicity/m2m/echoservice.py
dataplicity/m2m/fileservice.py
dataplicity/m2m/packetbase.py
dataplicity/m2m/packets.py
dataplicity/m2m/proxy.py
dataplicity/m2m/remoteprocess.py
dataplicity/m2m/wsclient.py
dataplicity/subcommands/__init__.py
dataplicity/subcommands/run.py
dataplicity/subcommands/version.py
utf_remote/__init__.py
utf_remote/__main__.py
utf_remote/_version.py
utf_remote/app.py
utf_remote/client.py
utf_remote/clockcheck.py
utf_remote/compat.py
utf_remote/constants.py
utf_remote/device_meta.py
utf_remote/disk_tools.py
utf_remote/iptool.py
utf_remote/jsonrpc.py
utf_remote/m2mmanager.py
utf_remote/portforward.py
utf_remote/rpi.py
utf_remote/subcommand.py
utf_remote/m2m/__init__.py
utf_remote/m2m/bencode.py
utf_remote/m2m/commandservice.py
utf_remote/m2m/dispatcher.py
utf_remote/m2m/echoservice.py
utf_remote/m2m/fileservice.py
utf_remote/m2m/packetbase.py
utf_remote/m2m/packets.py
utf_remote/m2m/proxy.py
utf_remote/m2m/remoteprocess.py
utf_remote/m2m/wsclient.py
utf_remote/subcommands/__init__.py
utf_remote/subcommands/run.py
utf_remote/subcommands/version.py
utf_remote-0.5.1.dist-info/LICENSE.txt
utf_remote-0.5.1.dist-info/METADATA
utf_remote-0.5.1.dist-info/WHEEL
utf_remote-0.5.1.dist-info/entry_points.txt
utf_remote-0.5.1.dist-info/top_level.txt
utf_remote-0.5.1.dist-info/zip-safe
utf_remote-0.5.1.dist-info/RECORD
