Metadata-Version: 2.1
Name: utf-remote
Version: 0.5.1
Summary: Platform for connected devices
Home-page: UNKNOWN
Author: Shayan Ahmed
Author-email: shayanahmed46@yahoo.com
License: UNKNOWN
Platform: any
Requires-Dist: enum34 (==1.1.6)
Requires-Dist: six (==1.10.0)
Requires-Dist: ws4py (==0.3.5)
